iembdfa
