Metadata-Version: 1.1
Name: iembdfa
Version: 1.8
Summary: pip install iembdafa 
Home-page: https://github.com/ccbrandenburg/financialanalyticsproject/0.1
Author: TeamD, Christopher Brandenburg
Author-email: cbrandenburg@student.ie.edu
License: MIT license
Keywords: iembdfa
Platform: UNKNOWN
Classifier: Development Status :: 2 - Pre-Alpha
Classifier: Intended Audience :: Developers
Classifier: License :: OSI Approved :: MIT License
Classifier: Natural Language :: English
Classifier: Programming Language :: Python :: 2
Classifier: Programming Language :: Python :: 2.6
Classifier: Programming Language :: Python :: 2.7
Classifier: Programming Language :: Python :: 3
Classifier: Programming Language :: Python :: 3.3
Classifier: Programming Language :: Python :: 3.4
Classifier: Programming Language :: Python :: 3.5
